{
    "1": {
        "Number": 1,
        "Type": "MC",
        "NumChoices": 4,
        "Topics": [
            "Numbers & Operations - Fractions"
        ],
        "SubTopics": [
            "Divide unit fractions by whole numbers and whole numbers by unit fractions."
        ],
        "SuppContent": [],
        "Content": [
            "Divide: 18 ÷ 1/12"
        ],
        "AnswerChoices": {
            "A": {
                "Choice": "2/3",
                "Key": {
                    "Correct": false,
                    "Rationale": "Inverts both 18 and 1/12 before multiplying (or divided 12 by 18).",
                    "Percent": 12
                }
            },
            "B": {
                "Choice": "1 1/2",
                "Key": {
                    "Correct": false,
                    "Rationale": "Divides 18 by 12.",
                    "Percent": 33
                }
            },
            "C": {
                "Choice": "30",
                "Key": {
                    "Correct": false,
                    "Rationale": "Inverts 1/12 but then adds 12 to 18.",
                    "Percent": 9
                }
            },
            "D": {
                "Choice": "216",
                "Key": {
                    "Correct": true,
                    "Rationale": "Correct.",
                    "Percent": 46
                }
            }
        }
    },
    "2": {
        "Number": 2,
        "Type": "MC",
        "NumChoices": 4,
        "Topics": [
            "Numbers & Operations In Base Ten"
        ],
        "SubTopics": [
            "Demonstrate an understanding that in a multi-digit number, a digit in one place represents 1/10 of what it represents in the place to its left."
        ],
        "SuppContent": [],
        "Content": [
            "Joe writes a number with a 3 in the tenths place. Ellie also writes a number with a 3 as a digit. The value of the 3 in Ellie’s number is 10 times the value of the 3 in Joe’s number. Which number could be the one Ellie wrote?"
        ],
        "AnswerChoices": {
            "A": {
                "Choice": "324.67",
                "Key": {
                    "Correct": false,
                    "Rationale": "Uses the tens place instead of the tenths place for the 3 in Joe’s number.",
                    "Percent": 21
                }
            },
            "B": {
                "Choice": "423.67",
                "Key": {
                    "Correct": true,
                    "Rationale": "Correct.",
                    "Percent": 46
                }
            },
            "C": {
                "Choice": "426.37",
                "Key": {
                    "Correct": false,
                    "Rationale": "Identifies a number that could be Joe’s number.",
                    "Percent": 19
                }
            },
            "D": {
                "Choice": "426.73",
                "Key": {
                    "Correct": false,
                    "Rationale": "Identifies a number using a 3 that is }1 of the value of the 3 in Joe’s number 10 instead of 10 times the value.",
                    "Percent": 14
                }
            }
        }
    },
    "3": {
        "Number": 3,
        "Type": "MC",
        "NumChoices": 4,
        "Topics": [
            "Numbers & Operations In Base Ten",
            "Numbers & Operations In Base Ten"
        ],
        "SubTopics": [
            "Compare two decimals to thousandths based on meanings of the digits in each place using >, =, and < symbols.",
            "Read and write decimals to thousandths using base-ten numerals, word form, and expanded form."
        ],
        "SuppContent": [],
        "Content": [
            "An inequality is shown below.",
            "4.205 < _____",
            "Which number could be placed into the blank to make the inequality true?"
        ],
        "AnswerChoices": {
            "A": {
                "Choice": "four and twenty-four hundredths",
                "Key": {
                    "Correct": true,
                    "Rationale": "Correct.",
                    "Percent": 48
                }
            },
            "B": {
                "Choice": "four and twenty-seven thousandths",
                "Key": {
                    "Correct": false,
                    "Rationale": "Compares 27 to 20.",
                    "Percent": 26
                }
            },
            "C": {
                "Choice": "four and two hundred five thousandths",
                "Key": {
                    "Correct": false,
                    "Rationale": "Selects an equal amount.",
                    "Percent": 17
                }
            },
            "D": {
                "Choice": "four and two hundred four thousandths",
                "Key": {
                    "Correct": false,
                    "Rationale": "Compares the numbers in the wrong direction.",
                    "Percent": 9
                }
            }
        }
    },
    "4": {
        "Number": 4,
        "Type": "MC",
        "NumChoices": 4,
        "Topics": [
            "Numbers & Operations In Base Ten",
            "Numbers & Operations In Base Ten",
            "Numbers & Operations In Base Ten"
        ],
        "SubTopics": [
            "Multiply multi-digit whole numbers (not to exceed three-digit by three-digit).",
            "Find whole-number quotients of whole numbers with up to four-digit dividends and two-digit divisors.",
            "Add, subtract, multiply, and divide decimals to hundredths (no divisors with decimals)."
        ],
        "SuppContent": [],
        "Content": [
            "A number is multiplied by 4, then divided by 2, and finally multiplied by 0.5. How does the result compare to the original number?"
        ],
        "AnswerChoices": {
            "A": {
                "Choice": "The result is the same as the original number.",
                "Key": {
                    "Correct": true,
                    "Rationale": "Correct.",
                    "Percent": 39
                }
            },
            "B": {
                "Choice": "The result is four times the value of the original number.",
                "Key": {
                    "Correct": false,
                    "Rationale": "Thinks the second and third operations “cancel” each other OR finds n × 4 × 2 × 0.5 OR finds n × 4 ÷ 2 ÷ 0.5.",
                    "Percent": 12
                }
            },
            "C": {
                "Choice": "The result is one-fourth the value of the original number.",
                "Key": {
                    "Correct": false,
                    "Rationale": "Finds n ÷ 4 × 2 × 0.5.",
                    "Percent": 12
                }
            },
            "D": {
                "Choice": "The result cannot be compared to the original number without knowing the original number.",
                "Key": {
                    "Correct": false,
                    "Rationale": "Does not understand how the operations are related.",
                    "Percent": 37
                }
            }
        }
    },
    "5": {
        "Number": 5,
        "Type": "MC",
        "NumChoices": 4,
        "Topics": [
            "Numbers & Operations - Fractions"
        ],
        "SubTopics": [
            "Use equivalent fractions as a strategy to add and subtract fractions."
        ],
        "SuppContent": [],
        "Content": [
            "The expression below shows two fractions being added.",
            "7/12 + 1/18",
            "Which expression could be used to find the sum of the two fractions?"
        ],
        "AnswerChoices": {
            "A": {
                "Choice": "5/6 + 2/6 + 1/6 + 1/6 + 1/6",
                "Key": {
                    "Correct": false,
                    "Rationale": "Decomposes numerators and denominators in attempt to get a common denominator.",
                    "Percent": 17
                }
            },
            "B": {
                "Choice": "5/30 + 1/30 + 1/30 + 1/30",
                "Key": {
                    "Correct": false,
                    "Rationale": "Adds numerators and adds denominators in original fractions.",
                    "Percent": 16
                }
            },
            "C": {
                "Choice": "15/36 + 6/36 + 1/36 + 1/36",
                "Key": {
                    "Correct": true,
                    "Rationale": "Correct.",
                    "Percent": 59
                }
            },
            "D": {
                "Choice": "30/72 + 12/72 + 2/72 + 1/72",
                "Key": {
                    "Correct": false,
                    "Rationale": "Does not notice that 1/72 should be 2/72.",
                    "Percent": 8
                }
            }
        }
    },
    "6": {
        "Number": 6,
        "Type": "MC",
        "NumChoices": 4,
        "Topics": [
            "Numbers & Operations - Fractions"
        ],
        "SubTopics": [
            "Solve addition and subtraction problems involving fractions (straight computation or word problems)."
        ],
        "SuppContent": [],
        "Content": [
            "Priya has two pieces of fabric.",
            "• One piece is 8/12 foot in length.",
            "• The other piece is 3/12 foot in length.",
            "Priya uses 9/12 foot of the fabric to make a pillowcase. How many feet of fabric does Priya have remaining?"
        ],
        "AnswerChoices": {
            "A": {
                "Choice": "1/6",
                "Key": {
                    "Correct": true,
                    "Rationale": "Correct.",
                    "Percent": 70
                }
            },
            "B": {
                "Choice": "1/3",
                "Key": {
                    "Correct": false,
                    "Rationale": "Finds 9/12 + 3/12 – 8/12.",
                    "Percent": 9
                }
            },
            "C": {
                "Choice": "11/12",
                "Key": {
                    "Correct": false,
                    "Rationale": "Finds total length of fabric before making pillowcase.",
                    "Percent": 14
                }
            },
            "D": {
                "Choice": "1 1/16",
                "Key": {
                    "Correct": false,
                    "Rationale": "Finds 8/12 + 9/12 – 3/12.",
                    "Percent": 7
                }
            }
        }
    },
    "7": {
        "Number": 7,
        "Type": "MC",
        "NumChoices": 4,
        "Topics": [
            "Numbers & Operations - Fractions"
        ],
        "SubTopics": [
            "Add and subtract fractions (including mixed numbers) with unlike denominators. (May include multiple methods and representations.)"
        ],
        "SuppContent": [],
        "Content": [
            "Tanya makes a paper volcano in science class. She spends 1/3 hour building the base, 1/6 hour shaping the cone, and 1/8 hour painting the outside. How many hours does Tanya spend making the volcano?"
        ],
        "AnswerChoices": {
            "A": {
                "Choice": "1/8",
                "Key": {
                    "Correct": false,
                    "Rationale": "Adds numerators (before conversion), but uses correct LCD and reduces.",
                    "Percent": 5
                }
            },
            "B": {
                "Choice": "3/17",
                "Key": {
                    "Correct": false,
                    "Rationale": "Adds numerators (before conversion), then denominators (before conversion).",
                    "Percent": 14
                }
            },
            "C": {
                "Choice": "5/8",
                "Key": {
                    "Correct": true,
                    "Rationale": "Correct.",
                    "Percent": 69
                }
            },
            "D": {
                "Choice": "15/17",
                "Key": {
                    "Correct": false,
                    "Rationale": "Adds numerators correctly (following conversion); adds denominators (before conversion).",
                    "Percent": 12
                }
            }
        }
    },
    "8": {
        "Number": 8,
        "Type": "MC",
        "NumChoices": 4,
        "Topics": [
            "Numbers & Operations - Fractions"
        ],
        "SubTopics": [
            "Solve multiplication and division problems involving fractions and whole numbers (straight computation or word problems)."
        ],
        "SuppContent": [],
        "Content": [
            "Cereal boxes are arranged on three different shelves in a grocery store.",
            "• The top shelf is 42 1/2 inches in length and 14 2/5 inches in width.",
            "• The middle shelf is 1 2/5 times the length of the top shelf and 1 1/2 times the width of the top shelf.",
            "• The bottom shelf is 4/5 times the length of the middle shelf and 3/4 times the width of the middle shelf.",
            "What are the length and the width of the bottom shelf?"
        ],
        "AnswerChoices": {
            "A": {
                "Choice": "length: 47 3/5 \n width: 12 3/20",
                "Key": {
                    "Correct": false,
                    "Rationale": "Calculates the correct length but subtracts the sum of “times the width” fractions of the middle and bottom shelves from the width of the top shelf.",
                    "Percent": 17
                }
            },
            "B": {
                "Choice": "length: 47 3/5 \n width: 16 1/5",
                "Key": {
                    "Correct": true,
                    "Rationale": "Correct.",
                    "Percent": 58
                }
            },
            "C": {
                "Choice": "length: 58 7/10 \n width: 20 17/20",
                "Key": {
                    "Correct": false,
                    "Rationale": "Subtracts “times the length” (4/5)and “times the width” (3/4)fractions in the bottom shelf bullet point from the correct length and width measurements of the middle shelf.",
                    "Percent": 13
                }
            },
            "D": {
                "Choice": "length: 59 1/2 \n width: 21 3/5",
                "Key": {
                    "Correct": false,
                    "Rationale": "Uses the middle shelf length and width.",
                    "Percent": 12
                }
            }
        }
    },
    "9": {
        "Number": 9,
        "Type": "MC",
        "NumChoices": 4,
        "Topics": [
            "Numbers & Operations - Fractions"
        ],
        "SubTopics": [
            "Demonstrate an understanding of multiplication as scaling (resizing)."
        ],
        "SuppContent": [],
        "Content": [
            "Two expressions are described below.",
            "expression R: multiply 35 by 6/5",
            "expression S: multiply 35 by 3/4",
            "Based on the descriptions, which statement is true?"
        ],
        "AnswerChoices": {
            "A": {
                "Choice": "The value of expression R is greater than 35 because 6/5 < 1.",
                "Key": {
                    "Correct": false,
                    "Rationale": "Uses the incorrect inequality.",
                    "Percent": 24
                }
            },
            "B": {
                "Choice": "The value of expression R is greater than 35 because 6/5 > 1.",
                "Key": {
                    "Correct": true,
                    "Rationale": "Correct.",
                    "Percent": 55
                }
            },
            "C": {
                "Choice": "The value of expression S is greater than 35 because 3/4 < 1.",
                "Key": {
                    "Correct": false,
                    "Rationale": "Uses the correct inequality for 3/4 but incorrectly states the effect of multiplying by a number less than 1.",
                    "Percent": 14
                }
            },
            "D": {
                "Choice": "The value of expression S is greater than 35 because 3/4 > 1.",
                "Key": {
                    "Correct": false,
                    "Rationale": "Does not use the correct inequality (although the statement matches the inequality used).",
                    "Percent": 7
                }
            }
        }
    },
    "10": {
        "Number": 10,
        "Type": "MC",
        "NumChoices": 4,
        "Topics": [
            "Operations & Algebraic Thinking"
        ],
        "SubTopics": [
            "Analyze and complete calculations by applying the order of operations."
        ],
        "SuppContent": [],
        "Content": [
            "The value of the expression shown below is 7.5.",
            "0.75(2 + 6 × 4 – 2 × 7 – 2)",
            "Each 2 in the expression is changed to a 3 to make a new expression. What is the difference in the values of the expressions?"
        ],
        "AnswerChoices": {
            "A": {
                "Choice": "1",
                "Key": {
                    "Correct": false,
                    "Rationale": "Assumes the change in the value of the expression will be 1 because 2 was increased by 1.",
                    "Percent": 17
                }
            },
            "B": {
                "Choice": "5.25",
                "Key": {
                    "Correct": true,
                    "Rationale": "Correct.",
                    "Percent": 39
                }
            },
            "C": {
                "Choice": "8.5",
                "Key": {
                    "Correct": false,
                    "Rationale": "Increases the original value of the expression by 1 because 2 was increased by 1.",
                    "Percent": 24
                }
            },
            "D": {
                "Choice": "22.5",
                "Key": {
                    "Correct": false,
                    "Rationale": "Multiplies 7.5 by 3.",
                    "Percent": 20
                }
            }
        }
    },
    "11": {
        "Number": 11,
        "Type": "MC",
        "NumChoices": 4,
        "Topics": [
            "Operations & Algebraic Thinking"
        ],
        "SubTopics": [
            "Write simple expressions that model calculations with numbers and interpret numerical expressions without evaluating them."
        ],
        "SuppContent": [],
        "Content": [
            "Which calculation is represented by the expression (5 + 2) ÷ 9?"
        ],
        "AnswerChoices": {
            "A": {
                "Choice": "divide five by nine, then add two",
                "Key": {
                    "Correct": false,
                    "Rationale": "Confuses order of operations.",
                    "Percent": 7
                }
            },
            "B": {
                "Choice": "divide two by nine, then add five",
                "Key": {
                    "Correct": false,
                    "Rationale": "Confuses order of operations.",
                    "Percent": 7
                }
            },
            "C": {
                "Choice": "divide the sum of five and two by nine",
                "Key": {
                    "Correct": true,
                    "Rationale": "Correct.",
                    "Percent": 55
                }
            },
            "D": {
                "Choice": "divide nine by the sum of five and two",
                "Key": {
                    "Correct": false,
                    "Rationale": "Reverses division.",
                    "Percent": 31
                }
            }
        }
    },
    "12": {
        "Number": 12,
        "Type": "MC",
        "NumChoices": 4,
        "Topics": [
            "Operations & Algebraic Thinking"
        ],
        "SubTopics": [
            "Create, extend, and analyze patterns."
        ],
        "SuppContent": [],
        "Content": [
            "The four shapes shown below repeat to form a pattern.",
            "problems/PA19G5M/media/12a.jpg",
            "The pattern continues. What is the 67th shape in the pattern?"
        ],
        "AnswerChoices": {
            "A": {
                "Choice": "problems/PA19G5M/media/12b.jpg",
                "Key": {
                    "Correct": false,
                    "Rationale": "Chooses 1 more instead of 1 less than a “complete” pattern (multiple of 4).",
                    "Percent": 18
                }
            },
            "B": {
                "Choice": "problems/PA19G5M/media/12c.jpg",
                "Key": {
                    "Correct": false,
                    "Rationale": "Selects the 66th shape.",
                    "Percent": 8
                }
            },
            "C": {
                "Choice": "problems/PA19G5M/media/12d.jpg",
                "Key": {
                    "Correct": true,
                    "Rationale": "Correct.",
                    "Percent": 61
                }
            },
            "D": {
                "Choice": "problems/PA19G5M/media/12e.jpg",
                "Key": {
                    "Correct": false,
                    "Rationale": "Selects the 68th shape (or 67 after the first).",
                    "Percent": 14
                }
            }
        }
    },
    "13": {
        "Number": 13,
        "Type": "MC",
        "NumChoices": 4,
        "Topics": [
            "Measurement & Data",
            "Measurement & Data"
        ],
        "SubTopics": [
            "Convert between different-sized measurement units within a given measurement system.",
            "Apply the formulas V = l × w × h and V = B × h for rectangular prisms to find volumes of right rectangular prisms with whole-number edge lengths in the context of solving real-world and mathematical problems."
        ],
        "SuppContent": [],
        "Content": [
            "A company uses boxes with the dimensions shown below. The width is in inches. The length and height are in feet.",
            "problems/PA19G5M/media/13a.jpg",
            "What is the volume, in cubic inches, of each box?"
        ],
        "AnswerChoices": {
            "A": {
                "Choice": "6 cubic inches",
                "Key": {
                    "Correct": false,
                    "Rationale": "Does not convert any of the measurements.",
                    "Percent": 34
                }
            },
            "B": {
                "Choice": "72 cubic inches",
                "Key": {
                    "Correct": false,
                    "Rationale": "Only converts one side to inches, and evaluates 12 × 6 × 1.",
                    "Percent": 18
                }
            },
            "C": {
                "Choice": "600 cubic inches",
                "Key": {
                    "Correct": false,
                    "Rationale": "Uses 10 inches to equal 1 foot.",
                    "Percent": 6
                }
            },
            "D": {
                "Choice": "864 cubic inches",
                "Key": {
                    "Correct": true,
                    "Rationale": "Correct.",
                    "Percent": 42
                }
            }
        }
    },
    "14": {
        "Number": 14,
        "Type": "MC",
        "NumChoices": 4,
        "Topics": [
            "Measurement & Data"
        ],
        "SubTopics": [
            "Solve problems involving computation of fractions by using information presented in line plots."
        ],
        "SuppContent": [],
        "Content": [
            "The line plot below shows the number of hours Mr. Jacobson spent writing for each of the last nine days.",
            "problems/PA19G5M/media/14a.jpg",
            "What is the total number of hours Mr. Jacobson spent writing over the last nine days?"
        ],
        "AnswerChoices": {
            "A": {
                "Choice": "31",
                "Key": {
                    "Correct": false,
                    "Rationale": "Adds only the whole numbers.",
                    "Percent": 11
                }
            },
            "B": {
                "Choice": "31 6/13",
                "Key": {
                    "Correct": false,
                    "Rationale": "Adds the numerators and denominators in all the fractions.",
                    "Percent": 11
                }
            },
            "C": {
                "Choice": "34 3/4",
                "Key": {
                    "Correct": true,
                    "Rationale": "Correct.",
                    "Percent": 63
                }
            },
            "D": {
                "Choice": "35",
                "Key": {
                    "Correct": false,
                    "Rationale": "Incorrectly combines the fractional parts of the 4 greatest values to get 2 instead of 1 + 3/4.",
                    "Percent": 15
                }
            }
        }
    },
    "15": {
        "Number": 15,
        "Type": "MC",
        "NumChoices": 4,
        "Topics": [
            "Measurement & Data"
        ],
        "SubTopics": [
            "Display and interpret data shown in tallies, tables, charts, pictographs, bar graphs, and line graphs, and use a title, appropriate scale, and labels. A grid will be provided to display data on bar graphs or line graphs."
        ],
        "SuppContent": [],
        "Content": [
            "A bar graph is shown below, but some of the information is missing.",
            "problems/PA19G5M/media/15a.jpg",
            "Which title and axis labels would be most appropriate for the graph?"
        ],
        "AnswerChoices": {
            "A": {
                "Choice": "Title: Leo’s Plants \n A: Type of Plant \n B: Average Height (inches)",
                "Key": {
                    "Correct": false,
                    "Rationale": "Selects title and axis labels that would work if labels were switched.",
                    "Percent": 26
                }
            },
            "B": {
                "Choice": "Title: Airplane Elevation \n A: Elevation (feet) \n B: Time since Start (minutes)",
                "Key": {
                    "Correct": false,
                    "Rationale": "Does not recognize the non-continuous aspect of the x-axis.",
                    "Percent": 17
                }
            },
            "C": {
                "Choice": "Title: Voting Results \n A: Number of Voters \n B: Candidate",
                "Key": {
                    "Correct": true,
                    "Rationale": "Correct.",
                    "Percent": 37
                }
            },
            "D": {
                "Choice": "Title: Movie Tickets \n A: Number of Tickets \n B: Total Cost ($)",
                "Key": {
                    "Correct": false,
                    "Rationale": "Does not recognize the non-continuous aspect of the x-axis.",
                    "Percent": 20
                }
            }
        }
    },
    "16": {
        "Number": 16,
        "Type": "MC",
        "NumChoices": 4,
        "Topics": [
            "Measurement & Data"
        ],
        "SubTopics": [
            "Use, describe, and develop procedures to solve problems involving volume."
        ],
        "SuppContent": [],
        "Content": [
            "The bottom of the rectangular prism shown below is covered by 1-inch cubes.",
            "problems/PA19G5M/media/16a.jpg",
            "The height of the prism is 3 inches. Which statement explains how to determine the volume, in cubic inches, of the rectangular prism?"
        ],
        "AnswerChoices": {
            "A": {
                "Choice": "Add two more layers of the number of cubes in the bottom layer: 15 + 15 + 15.",
                "Key": {
                    "Correct": true,
                    "Rationale": "Correct.",
                    "Percent": 46
                }
            },
            "B": {
                "Choice": "Multiply the number of cubes in the bottom layer two more times: 15 × 15 × 15.",
                "Key": {
                    "Correct": false,
                    "Rationale": "Confuses multiplication with addition.",
                    "Percent": 12
                }
            },
            "C": {
                "Choice": "Add 3 to the number of cubes in the length and width of the bottom layer: 3 + 5 + 3.",
                "Key": {
                    "Correct": false,
                    "Rationale": "Confuses adding layers with adding to the dimensions.",
                    "Percent": 13
                }
            },
            "D": {
                "Choice": "Multiply the number of cubes in the bottom layer by the length and width of the bottom layer: 15 × 5 × 3.",
                "Key": {
                    "Correct": false,
                    "Rationale": "Mixes adding layers with multiplying dimensions.",
                    "Percent": 29
                }
            }
        }
    }
}