{
    "Title": "Missouri Learning Standards > Mathematics > Grade 5",
    "Overview": "",
    "Goals": [],
    "Standards": [
        {
            "Key": "MO.M5.NBT",
            "Label": "Number Sense & Operations In Base Ten",
            "Examples": [],
            "Subs": [
                {
                    "Key": "MO.M5.NBT.A",
                    "Label": "Use place value system understanding to perform operations with multi-digit whole numbers to billions and decimals to thousandths.",
                    "Examples": [],
                    "Subs": [
                        {
                            "Key": "MO.M5.NBT.A.1",
                            "Label": "Read, write and identify numbers from billions to thousandths using number names, base ten numerals and expanded form.",
                            "Examples": [],
                            "Subs": []
                        },
                        {
                            "Key": "MO.M5.NBT.A.2",
                            "Label": "Compare two numbers from billions to thousandths using the symbols >, = or <, and justify the solution.",
                            "Examples": [],
                            "Subs": []
                        },
                        {
                            "Key": "MO.M5.NBT.A.3",
                            "Label": "Understand that in a multi-digit number, a digit represents 1/10 times what it would represents in the place to its left.",
                            "Examples": [],
                            "Subs": []
                        },
                        {
                            "Key": "MO.M5.NBT.A.4",
                            "Label": "Evaluate the value of powers of 10 and understand the relationship to the place value system.",
                            "Examples": [],
                            "Subs": []
                        },
                        {
                            "Key": "MO.M5.NBT.A.5",
                            "Label": "Round numbers from billions to thousandths place.",
                            "Examples": [],
                            "Subs": []
                        },
                        {
                            "Key": "MO.M5.NBT.A.6",
                            "Label": "Add and subtract multi- digit whole numbers and decimals to the thousandths place, and justify the solution.",
                            "Examples": [],
                            "Subs": []
                        },
                        {
                            "Key": "MO.M5.NBT.A.7",
                            "Label": "Multiply multi-digit whole numbers and decimals to the hundredths place, and justify the solution.",
                            "Examples": [],
                            "Subs": []
                        },
                        {
                            "Key": "MO.M5.NBT.A.8",
                            "Label": "Divide multi-digit whole numbers and decimals to the hundredths place using up to two-digit divisors and four-digit dividends, and justify the solution.",
                            "Examples": [],
                            "Subs": []
                        }
                    ]
                }
            ]
        },
        {
            "Key": "MO.M5.NF",
            "Label": "Number Sense & Operations In Fractions",
            "Examples": [],
            "Subs": [
                {
                    "Key": "MO.M5.NF.A",
                    "Label": "Understand the relationship between fractions and decimals (denominators that are factors of 100).",
                    "Examples": [],
                    "Subs": [
                        {
                            "Key": "MO.M5.NF.A.1",
                            "Label": "Understand that parts of a whole can be expressed as fractions and/or decimals.",
                            "Examples": [],
                            "Subs": []
                        },
                        {
                            "Key": "MO.M5.NF.A.2",
                            "Label": "Convert decimals to fractions and fractions to decimals.",
                            "Examples": [],
                            "Subs": []
                        },
                        {
                            "Key": "MO.M5.NF.A.3",
                            "Label": "Compare and order fractions and/or decimals to the thousandths place using the symbols >, = or <, and justify the solution.",
                            "Examples": [],
                            "Subs": []
                        }
                    ]
                },
                {
                    "Key": "MO.M5.NF.B",
                    "Label": "Perform operations and solve problems with fractions and decimals.",
                    "Examples": [],
                    "Subs": [
                        {
                            "Key": "MO.M5.NF.B.1",
                            "Label": "Estimate results of sums, differences and products with fractions and decimals to the thousandths.",
                            "Examples": [],
                            "Subs": []
                        },
                        {
                            "Key": "MO.M5.NF.B.2",
                            "Label": "Justify the reasonableness of a product when multiplying with fractions.",
                            "Examples": [],
                            "Subs": [
                                {
                                    "Key": "MO.M5.NF.B.2.a",
                                    "Label": "Estimate the size of the product based on the size of the two factors.",
                                    "Examples": [],
                                    "Subs": []
                                },
                                {
                                    "Key": "MO.M5.NF.B.2.b",
                                    "Label": "Explain why multiplying a given number by a fraction greater than 1 results in a product larger than the given number.",
                                    "Examples": [],
                                    "Subs": []
                                },
                                {
                                    "Key": "MO.M5.NF.B.2.c",
                                    "Label": "Explain why multiplying a given number by a fraction less than 1 results in a product smaller than the given number.",
                                    "Examples": [],
                                    "Subs": []
                                },
                                {
                                    "Key": "MO.M5.NF.B.2.d",
                                    "Label": "Explain why multiplying the numerator and denominator by the same number is equivalent to multiplying the fraction by 1.",
                                    "Examples": [],
                                    "Subs": []
                                }
                            ]
                        },
                        {
                            "Key": "MO.M5.NF.B.3",
                            "Label": "Solve problems involving addition and subtraction of fractions and mixed numbers with unlike denominators, and justify the solution.",
                            "Examples": [],
                            "Subs": []
                        },
                        {
                            "Key": "MO.M5.NF.B.4",
                            "Label": "Extend the concept of multiplication to multiply a fraction or whole number by a fraction.",
                            "Examples": [],
                            "Subs": [
                                {
                                    "Key": "MO.M5.NF.B.4.a",
                                    "Label": "Recognize the relationship between multiplying fractions and finding the areas of rectangles with fractional side lengths.",
                                    "Examples": [],
                                    "Subs": []
                                },
                                {
                                    "Key": "MO.M5.NF.B.4.b",
                                    "Label": "Calculate and interpret the product of a fraction by a whole number and a whole number by a fraction.",
                                    "Examples": [],
                                    "Subs": []
                                },
                                {
                                    "Key": "MO.M5.NF.B.4.c",
                                    "Label": "Calculate and interpret the product of two fractions less than one.",
                                    "Examples": [],
                                    "Subs": []
                                }
                            ]
                        },
                        {
                            "Key": "MO.M5.NF.B.5",
                            "Label": "Extend the concept of division to divide unit fractions and whole numbers by using visual fraction models and equations.",
                            "Examples": [],
                            "Subs": [
                                {
                                    "Key": "MO.M5.NF.B.5.a",
                                    "Label": "Calculate and interpret the quotient of a unit fraction by a non-zero whole number.",
                                    "Examples": [],
                                    "Subs": []
                                },
                                {
                                    "Key": "MO.M5.NF.B.5.b",
                                    "Label": "Calculate and interpret the quotient of a whole number by a unit fraction.",
                                    "Examples": [],
                                    "Subs": []
                                }
                            ]
                        }
                    ]
                }
            ]
        },
        {
            "Key": "MO.M5.RA",
            "Label": "Relationships & Algebraic Thinking",
            "Examples": [],
            "Subs": [
                {
                    "Key": "MO.M5.RA.A",
                    "Label": "Represent and analyze patterns and relationships.",
                    "Examples": [],
                    "Subs": [
                        {
                            "Key": "MO.M5.RA.A.1",
                            "Label": "Investigate the relationship between two numeric patterns.",
                            "Examples": [],
                            "Subs": [
                                {
                                    "Key": "MO.M5.RA.A.1.a",
                                    "Label": "Generate two numeric patterns given two rules.",
                                    "Examples": [],
                                    "Subs": []
                                },
                                {
                                    "Key": "MO.M5.RA.A.1.b",
                                    "Label": "Translate two numeric patterns into two sets of ordered pairs.",
                                    "Examples": [],
                                    "Subs": []
                                },
                                {
                                    "Key": "MO.M5.RA.A.1.c",
                                    "Label": "Graph numeric patterns on the Cartesian coordinate plane.",
                                    "Examples": [],
                                    "Subs": []
                                },
                                {
                                    "Key": "MO.M5.RA.A.1.d",
                                    "Label": "Identify the relationship between two numeric patterns.",
                                    "Examples": [],
                                    "Subs": []
                                }
                            ]
                        },
                        {
                            "Key": "MO.M5.RA.A.2",
                            "Label": "Write a rule to describe or explain a given numeric pattern.",
                            "Examples": [],
                            "Subs": []
                        }
                    ]
                },
                {
                    "Key": "MO.M5.RA.B",
                    "Label": "Write and interpret numerical expressions.",
                    "Examples": [],
                    "Subs": [
                        {
                            "Key": "MO.M5.RA.B.1",
                            "Label": "Write, evaluate and interpret numeric expressions using the order of operations.",
                            "Examples": [],
                            "Subs": []
                        },
                        {
                            "Key": "MO.M5.RA.B.2",
                            "Label": "Translate written expressions into algebraic expressions.",
                            "Examples": [],
                            "Subs": []
                        }
                    ]
                },
                {
                    "Key": "MO.M5.RA.C",
                    "Label": "Use the four operations to represent and solve problems.",
                    "Examples": [],
                    "Subs": [
                        {
                            "Key": "MO.M5.RA.C.1",
                            "Label": "Solve and justify multi-step problems involving variables, whole numbers, fractions and decimals.",
                            "Examples": [],
                            "Subs": []
                        }
                    ]
                }
            ]
        },
        {
            "Key": "MO.M5.GM",
            "Label": "Geometry & Measurement",
            "Examples": [],
            "Subs": [
                {
                    "Key": "MO.M5.GM.A",
                    "Label": "Classify two- and three-dimensional geometric shapes.",
                    "Examples": [],
                    "Subs": [
                        {
                            "Key": "MO.M5.GM.A.1",
                            "Label": "Understand that attributes belonging to a category of figures also belong to all subcategories.",
                            "Examples": [],
                            "Subs": []
                        },
                        {
                            "Key": "MO.M5.GM.A.2",
                            "Label": "Classify figures in a hierarchy based on properties.",
                            "Examples": [],
                            "Subs": []
                        },
                        {
                            "Key": "MO.M5.GM.A.3",
                            "Label": "Analyze and describe the properties of prisms and pyramids.",
                            "Examples": [],
                            "Subs": []
                        }
                    ]
                },
                {
                    "Key": "MO.M5.GM.B",
                    "Label": "Understand and compute volume.",
                    "Examples": [],
                    "Subs": [
                        {
                            "Key": "MO.M5.GM.B.1",
                            "Label": "Understand the concept of volume and recognize that volume is measured in cubic units.",
                            "Examples": [],
                            "Subs": [
                                {
                                    "Key": "MO.M5.GM.B.1.a",
                                    "Label": "Describe a cube with edge length 1 unit as a “unit cube” and is said to have “one cubic unit” of volume and can be used to measure volume.",
                                    "Examples": [],
                                    "Subs": []
                                },
                                {
                                    "Key": "MO.M5.GM.B.1.b",
                                    "Label": "Understand that the volume of a right rectangular prism can be found by stacking multiple layers of the base.",
                                    "Examples": [],
                                    "Subs": []
                                }
                            ]
                        },
                        {
                            "Key": "MO.M5.GM.B.2",
                            "Label": "Apply the formulas V = l × w × h and V = B × h for volume of right rectangular prisms with whole-number edge lengths.",
                            "Examples": [],
                            "Subs": []
                        }
                    ]
                },
                {
                    "Key": "MO.M5.GM.C",
                    "Label": "Graph points on the Cartesian coordinate plane within the first quadrant to solve problems.",
                    "Examples": [],
                    "Subs": [
                        {
                            "Key": "MO.M5.GM.C.1",
                            "Label": "Define a first quadrant Cartesian coordinate system.",
                            "Examples": [],
                            "Subs": [
                                {
                                    "Key": "MO.M5.GM.C.1.a",
                                    "Label": "Represent the axes as scaled perpendicular number lines that both intersect at 0, the origin.",
                                    "Examples": [],
                                    "Subs": []
                                },
                                {
                                    "Key": "MO.M5.GM.C.1.b",
                                    "Label": "Identify any point on the Cartesian coordinate plane by its ordered pair coordinates.",
                                    "Examples": [],
                                    "Subs": []
                                },
                                {
                                    "Key": "MO.M5.GM.C.1.c",
                                    "Label": "Define the first number in an ordered pair as the horizontal distance from the origin.",
                                    "Examples": [],
                                    "Subs": []
                                },
                                {
                                    "Key": "MO.M5.GM.C.1.d",
                                    "Label": "Define the second number in an ordered pair as the vertical distance from the origin.",
                                    "Examples": [],
                                    "Subs": []
                                }
                            ]
                        },
                        {
                            "Key": "MO.M5.GM.C.2",
                            "Label": "Plot and interpret points in the first quadrant of the Cartesian coordinate plane.",
                            "Examples": [],
                            "Subs": []
                        }
                    ]
                },
                {
                    "Key": "MO.M5.GM.D",
                    "Label": "Solve problems involving measurement and conversions within a measurement system.",
                    "Examples": [],
                    "Subs": [
                        {
                            "Key": "MO.M5.GM.D.1",
                            "Label": "Convert measurements of capacity, length and weight within a given measurement system.",
                            "Examples": [],
                            "Subs": []
                        },
                        {
                            "Key": "MO.M5.GM.D.2",
                            "Label": "Solve multi-step problems that require measurement conversions.",
                            "Examples": [],
                            "Subs": []
                        }
                    ]
                }
            ]
        },
        {
            "Key": "MO.M5.DS",
            "Label": "Data & Statistics",
            "Examples": [],
            "Subs": [
                {
                    "Key": "MO.M5.DS.A",
                    "Label": "Represent and analyze data.",
                    "Examples": [],
                    "Subs": [
                        {
                            "Key": "MO.M5.DS.A.1",
                            "Label": "Create a line graph to represent a data set, and analyze the data to answer questions and solve problems.",
                            "Examples": [],
                            "Subs": []
                        },
                        {
                            "Key": "MO.M5.DS.A.2",
                            "Label": "Create a line plot to represent a given or generated data set, and analyze the data to answer questions and solve problems, recognizing the outliers and generating the median.",
                            "Examples": [],
                            "Subs": []
                        }
                    ]
                }
            ]
        }
    ],
    "References": []
}