{
    "1": {
        "Number": 1,
        "Type": "MC",
        "NumChoices": 4,
        "Topics": [
            "Vocabulary Acquisition & Use"
        ],
        "SubTopics": [
            "Determine or clarify the meaning of unknown and multiple meaning words or phrases based on grade 8 reading and content, choosing flexibly from a range of strategies."
        ],
        "SuppContent": [
            "problems/MDG8E/supps/MDG8E-S1.json"
        ],
        "SuppTools": [],
        "Points": 1,
        "Explain": false,
        "Content": [
            "What is the meaning of the word PRIZE as it is used in paragraph 4?"
        ],
        "AnswerChoices": {
            "A": {
                "Choice": "to avoid breaking",
                "Key": {
                    "Correct": false,
                    "Rationale": "",
                    "Percent": 0
                }
            },
            "B": {
                "Choice": "to move by force",
                "Key": {
                    "Correct": true,
                    "Rationale": "",
                    "Percent": 0
                }
            },
            "C": {
                "Choice": "to insert carefully",
                "Key": {
                    "Correct": false,
                    "Rationale": "",
                    "Percent": 0
                }
            },
            "D": {
                "Choice": "to give a solution",
                "Key": {
                    "Correct": false,
                    "Rationale": "",
                    "Percent": 0
                }
            }
        },
        "Parts": {}
    },
    "2": {
        "Number": 2,
        "Type": "MP",
        "NumChoices": 0,
        "Topics": [
            "Reading Literature - Key Ideas & Details"
        ],
        "SubTopics": [
            "Analyze how particular lines of dialogue or incidents in a story or drama propel the action, reveal aspects of a character, or provoke a decision."
        ],
        "SuppContent": [
            "problems/MDG8E/supps/MDG8E-S1.json"
        ],
        "SuppTools": [],
        "Points": 2,
        "Explain": false,
        "Content": [
            ":ibox:THIS QUESTION HAS TWO PARTS."
        ],
        "AnswerChoices": {},
        "Parts": {
            "A": {
                "Type": "MC",
                "NumChoices": 4,
                "Points": 1,
                "Explain": false,
                "Content": [
                    "Based on the passage, which statement about the girl on the train is MOST LIKELY accurate?"
                ],
                "AnswerChoices": {
                    "A": {
                        "Choice": "She is jealous of Mira's family.",
                        "Key": {
                            "Correct": false,
                            "Rationale": "",
                            "Percent": 0
                        }
                    },
                    "B": {
                        "Choice": "She is traveling to the same destination as Mira.",
                        "Key": {
                            "Correct": false,
                            "Rationale": "",
                            "Percent": 0
                        }
                    },
                    "C": {
                        "Choice": "She has a strong impact on Mira.",
                        "Key": {
                            "Correct": true,
                            "Rationale": "",
                            "Percent": 0
                        }
                    },
                    "D": {
                        "Choice": "She has found an opportunity to talk with Mira.",
                        "Key": {
                            "Correct": false,
                            "Rationale": "",
                            "Percent": 0
                        }
                    }
                }
            },
            "B": {
                "Type": "MC",
                "NumChoices": 4,
                "Points": 1,
                "Explain": false,
                "Content": [
                    "Which quotation from the passage BEST supports the answer to Part A?"
                ],
                "AnswerChoices": {
                    "A": {
                        "Choice": "“... it's as if she's challenging me not to look away, to really see who she is.” (paragraph 1)",
                        "Key": {
                            "Correct": true,
                            "Rationale": "",
                            "Percent": 0
                        }
                    },
                    "B": {
                        "Choice": "“Everyone in the family laughs except the girl my age...” (paragraph 3)",
                        "Key": {
                            "Correct": false,
                            "Rationale": "",
                            "Percent": 0
                        }
                    },
                    "C": {
                        "Choice": "“She nods at me as if she's understood my plan...” (paragraph 4)",
                        "Key": {
                            "Correct": false,
                            "Rationale": "",
                            "Percent": 0
                        }
                    },
                    "D": {
                        "Choice": "“'I knew she wanted it, so I just sort of gave it to her.' ...” (paragraph 10)",
                        "Key": {
                            "Correct": false,
                            "Rationale": "",
                            "Percent": 0
                        }
                    }
                }
            }
        }
    },
    "3": {
        "Number": 3,
        "Type": "MP",
        "NumChoices": 0,
        "Topics": [
            "Reading Literature - Key Ideas & Details"
        ],
        "SubTopics": [
            "Analyze how particular lines of dialogue or incidents in a story or drama propel the action, reveal aspects of a character, or provoke a decision."
        ],
        "SuppContent": [
            "problems/MDG8E/supps/MDG8E-S1.json"
        ],
        "SuppTools": [],
        "Points": 2,
        "Explain": false,
        "Content": [
            ":ibox:THIS QUESTION HAS TWO PARTS."
        ],
        "AnswerChoices": {},
        "Parts": {
            "A": {
                "Type": "MC",
                "NumChoices": 4,
                "Points": 1,
                "Explain": false,
                "Content": [
                    "What aspect of Mira's character does paragraph 7 reveal?"
                ],
                "AnswerChoices": {
                    "A": {
                        "Choice": "Mira wants to help the girl have a better life.",
                        "Key": {
                            "Correct": true,
                            "Rationale": "",
                            "Percent": 0
                        }
                    },
                    "B": {
                        "Choice": "Mira wishes to become friends with the girl.",
                        "Key": {
                            "Correct": false,
                            "Rationale": "",
                            "Percent": 0
                        }
                    },
                    "C": {
                        "Choice": "Mira is concerned about what others think of her.",
                        "Key": {
                            "Correct": false,
                            "Rationale": "",
                            "Percent": 0
                        }
                    },
                    "D": {
                        "Choice": "Mira places little value on material objects.",
                        "Key": {
                            "Correct": false,
                            "Rationale": "",
                            "Percent": 0
                        }
                    }
                }
            },
            "B": {
                "Type": "MC",
                "NumChoices": 4,
                "Points": 1,
                "Explain": false,
                "Content": [
                    "Which quotation from paragraph 7 BEST supports the answer to Part A?"
                ],
                "AnswerChoices": {
                    "A": {
                        "Choice": "“... the girl reaches toward me and squeezes my hand tightly.”",
                        "Key": {
                            "Correct": false,
                            "Rationale": "",
                            "Percent": 0
                        }
                    },
                    "B": {
                        "Choice": "“... that it would be cowardly to look away.”",
                        "Key": {
                            "Correct": false,
                            "Rationale": "",
                            "Percent": 0
                        }
                    },
                    "C": {
                        "Choice": "“I'm still holding Nana Josie's charm.”",
                        "Key": {
                            "Correct": false,
                            "Rationale": "",
                            "Percent": 0
                        }
                    },
                    "D": {
                        "Choice": "“I wonder if she thinks that my charm can bring her luck.”",
                        "Key": {
                            "Correct": true,
                            "Rationale": "",
                            "Percent": 0
                        }
                    }
                }
            }
        }
    },
    "4": {
        "Number": 4,
        "Type": "MS",
        "NumChoices": 5,
        "Topics": [
            "Reading Literature - Key Ideas & Details"
        ],
        "SubTopics": [
            "Analyze how particular lines of dialogue or incidents in a story or drama propel the action, reveal aspects of a character, or provoke a decision."
        ],
        "SuppContent": [
            "problems/MDG8E/supps/MDG8E-S1.json"
        ],
        "SuppTools": [],
        "Points": 1,
        "Explain": false,
        "Content": [
            "Which TWO statements BEST describe the effects that Janu's words and actions have on Mira in paragraphs 9 through 14?"
        ],
        "AnswerChoices": {
            "A": {
                "Choice": "Mira feels embarrassed for giving away an important possession.",
                "Key": {
                    "Correct": true,
                    "Rationale": "",
                    "Percent": 0
                }
            },
            "B": {
                "Choice": "Mira considers the influence that her grandmother had on her actions.",
                "Key": {
                    "Correct": false,
                    "Rationale": "",
                    "Percent": 0
                }
            },
            "C": {
                "Choice": "Mira insists that her actions will have a positive impact in the end.",
                "Key": {
                    "Correct": false,
                    "Rationale": "",
                    "Percent": 0
                }
            },
            "D": {
                "Choice": "Mira realizes that her act of generosity may not have the intended result.",
                "Key": {
                    "Correct": true,
                    "Rationale": "",
                    "Percent": 0
                }
            },
            "E": {
                "Choice": "Mira believes herself incapable of explaining her true motivations.",
                "Key": {
                    "Correct": false,
                    "Rationale": "",
                    "Percent": 0
                }
            }
        },
        "Parts": {}
    },
    "5": {
        "Number": 5,
        "Type": "MC",
        "NumChoices": 4,
        "Topics": [
            "Reading Literature - Craft & Structure"
        ],
        "SubTopics": [
            "Analyze how differences in the points of view of the characters and the audience or reader (e.g., created through the use of dramatic irony) create such effects as suspense or humor."
        ],
        "SuppContent": [
            "problems/MDG8E/supps/MDG8E-S1.json"
        ],
        "SuppTools": [],
        "Points": 1,
        "Explain": false,
        "Content": [
            "How does telling the story from Mira's point of view create suspense?"
        ],
        "AnswerChoices": {
            "A": {
                "Choice": "The reader is unable to experience the shift in Mira's emotions.",
                "Key": {
                    "Correct": false,
                    "Rationale": "",
                    "Percent": 0
                }
            },
            "B": {
                "Choice": "The reader is unsure how other characters will react to Mira's actions.",
                "Key": {
                    "Correct": true,
                    "Rationale": "",
                    "Percent": 0
                }
            },
            "C": {
                "Choice": "The reader develops different opinions about the family than Mira.",
                "Key": {
                    "Correct": false,
                    "Rationale": "",
                    "Percent": 0
                }
            },
            "D": {
                "Choice": "The reader feels concerned with what might happen to Mira on the train.",
                "Key": {
                    "Correct": false,
                    "Rationale": "",
                    "Percent": 0
                }
            }
        },
        "Parts": {}
    },
    "6": {
        "Number": 6,
        "Type": "MP",
        "NumChoices": 0,
        "Topics": [
            "Reading Literature - Key Ideas & Details"
        ],
        "SubTopics": [
            "Determine a theme or central idea of a text and analyze its development over the course of the text, including its relationship to the characters, setting, and plot; provide an objective summary of the text."
        ],
        "SuppContent": [
            "problems/MDG8E/supps/MDG8E-S1.json"
        ],
        "SuppTools": [],
        "Points": 2,
        "Explain": false,
        "Content": [
            ":ibox:THIS QUESTION HAS TWO PARTS."
        ],
        "AnswerChoices": {},
        "Parts": {
            "A": {
                "Type": "MC",
                "NumChoices": 4,
                "Points": 1,
                "Explain": false,
                "Content": [
                    "Which theme is revealed through Mira's actions?"
                ],
                "AnswerChoices": {
                    "A": {
                        "Choice": "Sacrificing a personal item is like sacrificing a piece of one's past.",
                        "Key": {
                            "Correct": true,
                            "Rationale": "",
                            "Percent": 0
                        }
                    },
                    "B": {
                        "Choice": "Making sacrifices for others creates a sense of independence.",
                        "Key": {
                            "Correct": false,
                            "Rationale": "",
                            "Percent": 0
                        }
                    },
                    "C": {
                        "Choice": "Trying to help others improves the world for all.",
                        "Key": {
                            "Correct": false,
                            "Rationale": "",
                            "Percent": 0
                        }
                    },
                    "D": {
                        "Choice": "Providing guidance can make others dependent.",
                        "Key": {
                            "Correct": false,
                            "Rationale": "",
                            "Percent": 0
                        }
                    }
                }
            },
            "B": {
                "Type": "MC",
                "NumChoices": 4,
                "Points": 1,
                "Explain": false,
                "Content": [
                    "Which quotation from the passage BEST supports the answer to Part A?"
                ],
                "AnswerChoices": {
                    "A": {
                        "Choice": "“'And it just felt like the right thing to do!'” (paragraph 12)",
                        "Key": {
                            "Correct": false,
                            "Rationale": "",
                            "Percent": 0
                        }
                    },
                    "B": {
                        "Choice": "“'You don't understand the way things work here.'” (paragraph 13)",
                        "Key": {
                            "Correct": false,
                            "Rationale": "",
                            "Percent": 0
                        }
                    },
                    "C": {
                        "Choice": "“How could I have given away Nana Josie's charm?!” (paragraph 14)",
                        "Key": {
                            "Correct": true,
                            "Rationale": "",
                            "Percent": 0
                        }
                    },
                    "D": {
                        "Choice": "“I try to cover up my face as the tears spill over.” (paragraph 15)",
                        "Key": {
                            "Correct": false,
                            "Rationale": "",
                            "Percent": 0
                        }
                    }
                }
            }
        }
    },
    "7": {
        "Number": 7,
        "Type": "MP",
        "NumChoices": 0,
        "Topics": [
            "Reading Literature - Key Ideas & Details"
        ],
        "SubTopics": [
            "Analyze how particular lines of dialogue or incidents in a story or drama propel the action, reveal aspects of a character, or provoke a decision."
        ],
        "SuppContent": [
            "problems/MDG8E/supps/MDG8E-S1.json"
        ],
        "SuppTools": [],
        "Points": 2,
        "Explain": false,
        "Content": [
            ":ibox:THIS QUESTION HAS TWO PARTS."
        ],
        "AnswerChoices": {},
        "Parts": {
            "A": {
                "Type": "MC",
                "NumChoices": 4,
                "Points": 1,
                "Explain": false,
                "Content": [
                    "Based on the passage, which statement about Janu is MOST accurate?"
                ],
                "AnswerChoices": {
                    "A": {
                        "Choice": "Janu is critical of Mira's behavior, but he remains sympathetic to the family.",
                        "Key": {
                            "Correct": false,
                            "Rationale": "",
                            "Percent": 0
                        }
                    },
                    "B": {
                        "Choice": "Janu is tired of Mira's complaining, but he accepts it because he cares about her.",
                        "Key": {
                            "Correct": false,
                            "Rationale": "",
                            "Percent": 0
                        }
                    },
                    "C": {
                        "Choice": "Janu is confused by Mira's generosity, but he continues to act as her protector.",
                        "Key": {
                            "Correct": false,
                            "Rationale": "",
                            "Percent": 0
                        }
                    },
                    "D": {
                        "Choice": "Janu is frustrated with Mira's actions, but he is compassionate toward her.",
                        "Key": {
                            "Correct": true,
                            "Rationale": "",
                            "Percent": 0
                        }
                    }
                }
            },
            "B": {
                "Type": "MS",
                "NumChoices": 5,
                "Points": 1,
                "Explain": false,
                "Content": [
                    "Which TWO quotations from the passage, when taken together, support the answer to Part A?"
                ],
                "AnswerChoices": {
                    "A": {
                        "Choice": "“Janu shrugs. 'Was it valuable?'” (paragraph 9)",
                        "Key": {
                            "Correct": false,
                            "Rationale": "",
                            "Percent": 0
                        }
                    },
                    "B": {
                        "Choice": "“His anger gives a hard, cold edge to his voice.” (paragraph 13)",
                        "Key": {
                            "Correct": true,
                            "Rationale": "",
                            "Percent": 0
                        }
                    },
                    "C": {
                        "Choice": "“I feel sick. Of course he's right.” (paragraph 14)",
                        "Key": {
                            "Correct": false,
                            "Rationale": "",
                            "Percent": 0
                        }
                    },
                    "D": {
                        "Choice": "“He must think I'm always crying...” (paragraph 15)",
                        "Key": {
                            "Correct": false,
                            "Rationale": "",
                            "Percent": 0
                        }
                    },
                    "E": {
                        "Choice": "“... takes my wrist gently in his hands. 'I'm sorry,' he says.” (paragraph 16)",
                        "Key": {
                            "Correct": true,
                            "Rationale": "",
                            "Percent": 0
                        }
                    }
                }
            }
        }
    },
    "8": {
        "Number": 8,
        "Type": "MC",
        "NumChoices": 4,
        "Topics": [
            "Reading Literature - Key Ideas & Details"
        ],
        "SubTopics": [
            "Analyze how particular lines of dialogue or incidents in a story or drama propel the action, reveal aspects of a character, or provoke a decision."
        ],
        "SuppContent": [
            "problems/MDG8E/supps/MDG8E-S1.json"
        ],
        "SuppTools": [],
        "Points": 1,
        "Explain": false,
        "Content": [
            "How do Mira's and Janu's actions create irony in the passage?"
        ],
        "AnswerChoices": {
            "A": {
                "Choice": "Janu refuses food from the mother on the train, but Mira wonders if they should accept it.",
                "Key": {
                    "Correct": false,
                    "Rationale": "",
                    "Percent": 0
                }
            },
            "B": {
                "Choice": "Mira unhappily gives away the charm bracelet, and Janu angrily criticizes her decision.",
                "Key": {
                    "Correct": false,
                    "Rationale": "",
                    "Percent": 0
                }
            },
            "C": {
                "Choice": "Mira tries to understand the emotions of the girl on the train, but she does not realize that Janu is angry.",
                "Key": {
                    "Correct": false,
                    "Rationale": "",
                    "Percent": 0
                }
            },
            "D": {
                "Choice": "Janu gives the little girl a coin, but he scolds Mira for giving away her charm bracelet.",
                "Key": {
                    "Correct": true,
                    "Rationale": "",
                    "Percent": 0
                }
            }
        },
        "Parts": {}
    },
    "9": {
        "Number": 9,
        "Type": "MC",
        "NumChoices": 4,
        "Topics": [
            "Vocabulary Acquisition & Use"
        ],
        "SubTopics": [
            "Determine or clarify the meaning of unknown and multiple meaning words or phrases based on grade 8 reading and content, choosing flexibly from a range of strategies."
        ],
        "SuppContent": [
            "problems/MDG8E/supps/MDG8E-S2.json"
        ],
        "SuppTools": [],
        "Points": 1,
        "Explain": false,
        "Content": [
            "What is the meaning of the word RENDERED as it is used in paragraph 2?"
        ],
        "AnswerChoices": {
            "A": {
                "Choice": "provided or given a service",
                "Key": {
                    "Correct": false,
                    "Rationale": "",
                    "Percent": 0
                }
            },
            "B": {
                "Choice": "delivered a judgment or handed over",
                "Key": {
                    "Correct": false,
                    "Rationale": "",
                    "Percent": 0
                }
            },
            "C": {
                "Choice": "made or caused to be",
                "Key": {
                    "Correct": true,
                    "Rationale": "",
                    "Percent": 0
                }
            },
            "D": {
                "Choice": "suggested or explained a meaning",
                "Key": {
                    "Correct": false,
                    "Rationale": "",
                    "Percent": 0
                }
            }
        },
        "Parts": {}
    },
    "10": {
        "Number": 10,
        "Type": "MP",
        "NumChoices": 0,
        "Topics": [
            "Vocabulary Acquisition & Use"
        ],
        "SubTopics": [
            "Demonstrate understanding of figurative language, word relationships, and nuances in word meanings."
        ],
        "SuppContent": [
            "problems/MDG8E/supps/MDG8E-S2.json"
        ],
        "SuppTools": [],
        "Points": 2,
        "Explain": false,
        "Content": [
            ":ibox:THIS QUESTION HAS TWO PARTS."
        ],
        "AnswerChoices": {},
        "Parts": {
            "A": {
                "Type": "MC",
                "NumChoices": 4,
                "Points": 1,
                "Explain": false,
                "Content": [
                    "In paragraph 3, what does the phrase s͟k͟i͟r͟t͟i͟n͟g͟ ͟t͟h͟e͟ ͟w͟o͟r͟k͟ ͟o͟f͟ ͟d͟e͟c͟o͟d͟i͟n͟g mean?"
                ],
                "AnswerChoices": {
                    "A": {
                        "Choice": "grasping the meaning without actually reading the words",
                        "Key": {
                            "Correct": true,
                            "Rationale": "",
                            "Percent": 0
                        }
                    },
                    "B": {
                        "Choice": "focusing on the specific meaning of each individual word",
                        "Key": {
                            "Correct": false,
                            "Rationale": "",
                            "Percent": 0
                        }
                    },
                    "C": {
                        "Choice": "visualizing words to comprehend their meaning",
                        "Key": {
                            "Correct": false,
                            "Rationale": "",
                            "Percent": 0
                        }
                    },
                    "D": {
                        "Choice": "creating a new way to understand word meanings",
                        "Key": {
                            "Correct": false,
                            "Rationale": "",
                            "Percent": 0
                        }
                    }
                }
            },
            "B": {
                "Type": "MC",
                "NumChoices": 4,
                "Points": 1,
                "Explain": false,
                "Content": [
                    "Which phrase from paragraph 3 BEST supports the answer to Part A?"
                ],
                "AnswerChoices": {
                    "A": {
                        "Choice": "“they overlap considerably”",
                        "Key": {
                            "Correct": false,
                            "Rationale": "",
                            "Percent": 0
                        }
                    },
                    "B": {
                        "Choice": "“a good workaround”",
                        "Key": {
                            "Correct": true,
                            "Rationale": "",
                            "Percent": 0
                        }
                    },
                    "C": {
                        "Choice": "“the translation of print”",
                        "Key": {
                            "Correct": false,
                            "Rationale": "",
                            "Percent": 0
                        }
                    },
                    "D": {
                        "Choice": "“words in the mind”",
                        "Key": {
                            "Correct": false,
                            "Rationale": "",
                            "Percent": 0
                        }
                    }
                }
            }
        }
    },
    "11": {
        "Number": 11,
        "Type": "MC",
        "NumChoices": 4,
        "Topics": [
            "Reading Information - Craft & Structure"
        ],
        "SubTopics": [
            "Analyze in detail the structure of a specific paragraph in a text, including the role of particular sentences in developing and refining a key concept."
        ],
        "SuppContent": [
            "problems/MDG8E/supps/MDG8E-S2.json"
        ],
        "SuppTools": [],
        "Points": 1,
        "Explain": false,
        "Content": [
            "In paragraph 6, how does the phrase “Wherefore art thou Romeo?” from Romeo and Juliet expand upon the information presented in paragraph 5?"
        ],
        "AnswerChoices": {
            "A": {
                "Choice": "It reinforces the idea that skilled readers make inferences about prosody that help them with print texts.",
                "Key": {
                    "Correct": false,
                    "Rationale": "",
                    "Percent": 0
                }
            },
            "B": {
                "Choice": "It clarifies the important similarities between the experience of reading a text and listening to an audio version.",
                "Key": {
                    "Correct": false,
                    "Rationale": "",
                    "Percent": 0
                }
            },
            "C": {
                "Choice": "It explains why the experiment resulted in a connection between recorded speed and reading speed.",
                "Key": {
                    "Correct": false,
                    "Rationale": "",
                    "Percent": 0
                }
            },
            "D": {
                "Choice": "It reveals that audio versions can sometimes help readers build comprehension differently from print texts.",
                "Key": {
                    "Correct": true,
                    "Rationale": "",
                    "Percent": 0
                }
            }
        },
        "Parts": {}
    },
    "12": {
        "Number": 12,
        "Type": "MP",
        "NumChoices": 0,
        "Topics": [
            "Reading Information - Key Ideas & Details"
        ],
        "SubTopics": [
            "Analyze how a text makes connections among and distinctions between individuals, ideas, or events (e.g., through comparisons, analogies, or categories)."
        ],
        "SuppContent": [
            "problems/MDG8E/supps/MDG8E-S2.json"
        ],
        "SuppTools": [],
        "Points": 2,
        "Explain": false,
        "Content": [
            ":ibox:THIS QUESTION HAS TWO PARTS."
        ],
        "AnswerChoices": {},
        "Parts": {
            "A": {
                "Type": "MC",
                "NumChoices": 4,
                "Points": 1,
                "Explain": false,
                "Content": [
                    "In paragraph 8 of the passage, the experiments develop the idea that"
                ],
                "AnswerChoices": {
                    "A": {
                        "Choice": "spending more time reading the beginning of texts can provide access to information presented later.",
                        "Key": {
                            "Correct": true,
                            "Rationale": "",
                            "Percent": 0
                        }
                    },
                    "B": {
                        "Choice": "organizing a written text is made easier through the use of conventions.",
                        "Key": {
                            "Correct": false,
                            "Rationale": "",
                            "Percent": 0
                        }
                    },
                    "C": {
                        "Choice": "reading print text takes longer than listening to audiobooks.",
                        "Key": {
                            "Correct": false,
                            "Rationale": "",
                            "Percent": 0
                        }
                    },
                    "D": {
                        "Choice": "studying foundational ideas before reading a text has no bearing on understanding of the material.",
                        "Key": {
                            "Correct": false,
                            "Rationale": "",
                            "Percent": 0
                        }
                    }
                }
            },
            "B": {
                "Type": "MC",
                "NumChoices": 4,
                "Points": 1,
                "Explain": false,
                "Content": [
                    "Which quotation from the passage BEST supports the answer to Part A?"
                ],
                "AnswerChoices": {
                    "A": {
                        "Choice": "“Note that the subject matter was difficult, and the goal wasn't pleasure but learning.” (paragraph 7)",
                        "Key": {
                            "Correct": false,
                            "Rationale": "",
                            "Percent": 0
                        }
                    },
                    "B": {
                        "Choice": "“... expository essays more likely include unfamiliar content and require more strategic reading.” (paragraph 9)",
                        "Key": {
                            "Correct": true,
                            "Rationale": "",
                            "Percent": 0
                        }
                    },
                    "C": {
                        "Choice": "“Print may be best for lingering over words or ideas, but audiobooks add literacy...” (paragraph 12)",
                        "Key": {
                            "Correct": false,
                            "Rationale": "",
                            "Percent": 0
                        }
                    },
                    "D": {
                        "Choice": "“You'll just get different things out of the experience.” (paragraph 13)",
                        "Key": {
                            "Correct": false,
                            "Rationale": "",
                            "Percent": 0
                        }
                    }
                }
            }
        }
    },
    "13": {
        "Number": 13,
        "Type": "MP",
        "NumChoices": 0,
        "Topics": [
            "Reading Information - Key Ideas & Details"
        ],
        "SubTopics": [
            "Cite the textual evidence that most strongly supports an analysis of what the text says explicitly as well as inferences drawn from the text."
        ],
        "SuppContent": [
            "problems/MDG8E/supps/MDG8E-S2.json"
        ],
        "SuppTools": [],
        "Points": 2,
        "Explain": false,
        "Content": [
            ":ibox:THIS QUESTION HAS TWO PARTS."
        ],
        "AnswerChoices": {},
        "Parts": {
            "A": {
                "Type": "MC",
                "NumChoices": 4,
                "Points": 1,
                "Explain": false,
                "Content": [
                    "According to the passage, which of the following is a benefit of print texts?"
                ],
                "AnswerChoices": {
                    "A": {
                        "Choice": "Print texts provide symbols for understanding prosody in dramatic works.",
                        "Key": {
                            "Correct": false,
                            "Rationale": "",
                            "Percent": 0
                        }
                    },
                    "B": {
                        "Choice": "Print texts result in higher scores on written quizzes for scientific subjects.",
                        "Key": {
                            "Correct": true,
                            "Rationale": "",
                            "Percent": 0
                        }
                    },
                    "C": {
                        "Choice": "Print texts are commonly viewed as the preferred format for book clubs.",
                        "Key": {
                            "Correct": false,
                            "Rationale": "",
                            "Percent": 0
                        }
                    },
                    "D": {
                        "Choice": "Print texts allow readers to decide on their own interpretations of a text.",
                        "Key": {
                            "Correct": false,
                            "Rationale": "",
                            "Percent": 0
                        }
                    }
                }
            },
            "B": {
                "Type": "MC",
                "NumChoices": 4,
                "Points": 1,
                "Explain": false,
                "Content": [
                    "Which quotation from the passage BEST supports the answer to Part A?"
                ],
                "AnswerChoices": {
                    "A": {
                        "Choice": "“But today the question I get most often is, 'Is it cheating if I listen to an audiobook for my book club?'” (paragraph 1)",
                        "Key": {
                            "Correct": false,
                            "Rationale": "",
                            "Percent": 0
                        }
                    },
                    "B": {
                        "Choice": "“'What a great party' can be a sincere compliment or sarcastic put- down, but they look identical on the page.” (paragraph 5)",
                        "Key": {
                            "Correct": false,
                            "Rationale": "",
                            "Percent": 0
                        }
                    },
                    "C": {
                        "Choice": "“... the readers scored 81 percent and the listeners 59 percent.” (paragraph 7)",
                        "Key": {
                            "Correct": true,
                            "Rationale": "",
                            "Percent": 0
                        }
                    },
                    "D": {
                        "Choice": "“... all in the service of hearing what writers are actually trying to tell us.” (paragraph 14)",
                        "Key": {
                            "Correct": false,
                            "Rationale": "",
                            "Percent": 0
                        }
                    }
                }
            }
        }
    },
    "14": {
        "Number": 14,
        "Type": "MP",
        "NumChoices": 0,
        "Topics": [
            "Reading Information - Key Ideas & Details"
        ],
        "SubTopics": [
            "Determine a central idea of a text and analyze its development over the course of the text, including its relationship to supporting ideas; provide an objective summary of the text."
        ],
        "SuppContent": [
            "problems/MDG8E/supps/MDG8E-S2.json"
        ],
        "SuppTools": [],
        "Points": 2,
        "Explain": false,
        "Content": [
            ":ibox:THIS QUESTION HAS TWO PARTS."
        ],
        "AnswerChoices": {},
        "Parts": {
            "A": {
                "Type": "MC",
                "NumChoices": 4,
                "Points": 1,
                "Explain": false,
                "Content": [
                    "Based on information in the passage, what is one conclusion that can be drawn about audiobooks?"
                ],
                "AnswerChoices": {
                    "A": {
                        "Choice": "Audiobooks teach people to become better readers.",
                        "Key": {
                            "Correct": false,
                            "Rationale": "",
                            "Percent": 0
                        }
                    },
                    "B": {
                        "Choice": "The popularity of audiobooks will continue to increase.",
                        "Key": {
                            "Correct": true,
                            "Rationale": "",
                            "Percent": 0
                        }
                    },
                    "C": {
                        "Choice": "The format of audiobooks will likely remain the same.",
                        "Key": {
                            "Correct": false,
                            "Rationale": "",
                            "Percent": 0
                        }
                    },
                    "D": {
                        "Choice": "Audiobooks are more often preferred by young people.",
                        "Key": {
                            "Correct": false,
                            "Rationale": "",
                            "Percent": 0
                        }
                    }
                }
            },
            "B": {
                "Type": "MS",
                "NumChoices": 5,
                "Points": 1,
                "Explain": false,
                "Content": [
                    "Select TWO quotations from the passage that BEST support the conclusion in Part A."
                ],
                "AnswerChoices": {
                    "A": {
                        "Choice": "“... sales have doubled in the last five years...” (paragraph 2)",
                        "Key": {
                            "Correct": true,
                            "Rationale": "",
                            "Percent": 0
                        }
                    },
                    "B": {
                        "Choice": "“... a skill that seems quaint and whose value is open to debate.” (paragraph 2)",
                        "Key": {
                            "Correct": false,
                            "Rationale": "",
                            "Percent": 0
                        }
                    },
                    "C": {
                        "Choice": "“... different books invite different ways that you want to read them...” (paragraph 13)",
                        "Key": {
                            "Correct": false,
                            "Rationale": "",
                            "Percent": 0
                        }
                    },
                    "D": {
                        "Choice": "“... authors are writing more works specifically meant to be heard.” (paragraph 13)",
                        "Key": {
                            "Correct": true,
                            "Rationale": "",
                            "Percent": 0
                        }
                    },
                    "E": {
                        "Choice": "“Our richest experiences will come not from treating print and audio interchangeably...” (paragraph 14)",
                        "Key": {
                            "Correct": false,
                            "Rationale": "",
                            "Percent": 0
                        }
                    }
                }
            }
        }
    },
    "15": {
        "Number": 15,
        "Type": "MP",
        "NumChoices": 0,
        "Topics": [
            "Reading Information - Craft & Structure"
        ],
        "SubTopics": [
            "Determine an author's point of view or purpose in a text and analyze how the author acknowledges and responds to conflicting evidence or viewpoints."
        ],
        "SuppContent": [
            "problems/MDG8E/supps/MDG8E-S2.json"
        ],
        "SuppTools": [],
        "Points": 2,
        "Explain": false,
        "Content": [
            ":ibox:THIS QUESTION HAS TWO PARTS."
        ],
        "AnswerChoices": {},
        "Parts": {
            "A": {
                "Type": "MC",
                "NumChoices": 4,
                "Points": 1,
                "Explain": false,
                "Content": [
                    "What is the author's main purpose in writing the passage?"
                ],
                "AnswerChoices": {
                    "A": {
                        "Choice": "to argue that print texts and audiobooks both provide unique benefits",
                        "Key": {
                            "Correct": true,
                            "Rationale": "",
                            "Percent": 0
                        }
                    },
                    "B": {
                        "Choice": "to explain why audiobooks are likely to change in the future by adopting features from print texts",
                        "Key": {
                            "Correct": false,
                            "Rationale": "",
                            "Percent": 0
                        }
                    },
                    "C": {
                        "Choice": "to inform about the many benefits of audiobooks for individuals with dyslexia and other learning disabilities",
                        "Key": {
                            "Correct": false,
                            "Rationale": "",
                            "Percent": 0
                        }
                    },
                    "D": {
                        "Choice": "to encourage people to read only print texts when they need to retain information",
                        "Key": {
                            "Correct": false,
                            "Rationale": "",
                            "Percent": 0
                        }
                    }
                }
            },
            "B": {
                "Type": "MC",
                "NumChoices": 4,
                "Points": 1,
                "Explain": false,
                "Content": [
                    "Which quotation from the passage BEST supports the answer to Part A?"
                ],
                "AnswerChoices": {
                    "A": {
                        "Choice": "“Although decoding is serious work for beginning readers, it's automatic by high school...” (paragraph 3)",
                        "Key": {
                            "Correct": false,
                            "Rationale": "",
                            "Percent": 0
                        }
                    },
                    "B": {
                        "Choice": "“Experiments show readers actually take longer to read the first sentence of a paragraph...” (paragraph 8)",
                        "Key": {
                            "Correct": false,
                            "Rationale": "",
                            "Percent": 0
                        }
                    },
                    "C": {
                        "Choice": "“... although one core process of comprehension serves both listening and reading, difficult texts demand additional mental strategies.” (paragraph 9)",
                        "Key": {
                            "Correct": false,
                            "Rationale": "",
                            "Percent": 0
                        }
                    },
                    "D": {
                        "Choice": "“... understanding the differences between them and figuring out how to use them to our advantage...” (paragraph 14)",
                        "Key": {
                            "Correct": true,
                            "Rationale": "",
                            "Percent": 0
                        }
                    }
                }
            }
        }
    },
    "16": {
        "Number": 16,
        "Type": "MC",
        "NumChoices": 4,
        "Topics": [
            "Vocabulary Acquisition & Use"
        ],
        "SubTopics": [
            "Determine or clarify the meaning of unknown and multiple meaning words or phrases based on grade 8 reading and content, choosing flexibly from a range of strategies."
        ],
        "SuppContent": [
            "problems/MDG8E/supps/MDG8E-S3.json"
        ],
        "SuppTools": [],
        "Points": 1,
        "Explain": false,
        "Content": [
            "In paragraph 3 of the passage from Banner in the Sky, what is the meaning of the word AGILELY?"
        ],
        "AnswerChoices": {
            "A": {
                "Choice": "with strength",
                "Key": {
                    "Correct": false,
                    "Rationale": "",
                    "Percent": 0
                }
            },
            "B": {
                "Choice": "with ease",
                "Key": {
                    "Correct": true,
                    "Rationale": "",
                    "Percent": 0
                }
            },
            "C": {
                "Choice": "with courage",
                "Key": {
                    "Correct": false,
                    "Rationale": "",
                    "Percent": 0
                }
            },
            "D": {
                "Choice": "with purpose",
                "Key": {
                    "Correct": false,
                    "Rationale": "",
                    "Percent": 0
                }
            }
        },
        "Parts": {}
    },
    "17": {
        "Number": 17,
        "Type": "MP",
        "NumChoices": 0,
        "Topics": [
            "Reading Literature - Key Ideas & Details"
        ],
        "SubTopics": [
            "Cite the textual evidence that most strongly supports an analysis of what the text says explicitly as well as inferences drawn from the text."
        ],
        "SuppContent": [
            "problems/MDG8E/supps/MDG8E-S3.json"
        ],
        "SuppTools": [],
        "Points": 2,
        "Explain": false,
        "Content": [
            ":ibox:THIS QUESTION HAS TWO PARTS."
        ],
        "AnswerChoices": {},
        "Parts": {
            "A": {
                "Type": "MC",
                "NumChoices": 4,
                "Points": 1,
                "Explain": false,
                "Content": [
                    "In the passage from Banner in the Sky, why does Rudi slow his pace as he climbs higher into the mountains?"
                ],
                "AnswerChoices": {
                    "A": {
                        "Choice": "He is tired because he is not accustomed to hiking long distances.",
                        "Key": {
                            "Correct": false,
                            "Rationale": "",
                            "Percent": 0
                        }
                    },
                    "B": {
                        "Choice": "He is less worried about being discovered by someone who knows him.",
                        "Key": {
                            "Correct": true,
                            "Rationale": "",
                            "Percent": 0
                        }
                    },
                    "C": {
                        "Choice": "He wants to stop and talk with other hikers on the mountain.",
                        "Key": {
                            "Correct": false,
                            "Rationale": "",
                            "Percent": 0
                        }
                    },
                    "D": {
                        "Choice": "He needs to focus more carefully as the hike gets steeper.",
                        "Key": {
                            "Correct": false,
                            "Rationale": "",
                            "Percent": 0
                        }
                    }
                }
            },
            "B": {
                "Type": "MC",
                "NumChoices": 4,
                "Points": 1,
                "Explain": false,
                "Content": [
                    "Which quotation from the passage BEST supports the answer to Part A?"
                ],
                "AnswerChoices": {
                    "A": {
                        "Choice": "“... others who might have known and questioned him were back in the town or on their farms.” (paragraph 4)",
                        "Key": {
                            "Correct": true,
                            "Rationale": "",
                            "Percent": 0
                        }
                    },
                    "B": {
                        "Choice": "“'Grüss Gott,' he said—'God's Greetings'— in the ancient salutation of the Alps.” (paragraph 5)",
                        "Key": {
                            "Correct": false,
                            "Rationale": "",
                            "Percent": 0
                        }
                    },
                    "C": {
                        "Choice": "“His feet, through the soles of his shoes, moulded themselves to each hump and crevice of the path.” (paragraph 6)",
                        "Key": {
                            "Correct": false,
                            "Rationale": "",
                            "Percent": 0
                        }
                    },
                    "D": {
                        "Choice": "“Partly, this was because of his slimness, his lightness of muscle and bone...” (paragraph 7)",
                        "Key": {
                            "Correct": false,
                            "Rationale": "",
                            "Percent": 0
                        }
                    }
                }
            }
        }
    },
    "18": {
        "Number": 18,
        "Type": "MS",
        "NumChoices": 6,
        "Topics": [
            "Reading Literature - Craft & Structure"
        ],
        "SubTopics": [
            "Determine the meaning of words and phrases as they are used in a text, including figurative and connotative meanings; analyze the impact of specific word choices on meaning and tone, including analogies or allusions to other texts."
        ],
        "SuppContent": [
            "problems/MDG8E/supps/MDG8E-S4.json"
        ],
        "SuppTools": [],
        "Points": 1,
        "Explain": false,
        "Content": [
            "Which THREE phrases from paragraph 2 of the passage from Gathering Blue BEST indicate the complexity of the Singer's robe?"
        ],
        "AnswerChoices": {
            "A": {
                "Choice": "“... the art of dye.”",
                "Key": {
                    "Correct": false,
                    "Rationale": "",
                    "Percent": 0
                }
            },
            "B": {
                "Choice": "“... from her stained hands ...”",
                "Key": {
                    "Correct": false,
                    "Rationale": "",
                    "Percent": 0
                }
            },
            "C": {
                "Choice": "“... rare ornamentation ...”",
                "Key": {
                    "Correct": true,
                    "Rationale": "",
                    "Percent": 0
                }
            },
            "D": {
                "Choice": "“... richly embroidered.”",
                "Key": {
                    "Correct": true,
                    "Rationale": "",
                    "Percent": 0
                }
            },
            "E": {
                "Choice": "“... intricate scenes ...”",
                "Key": {
                    "Correct": true,
                    "Rationale": "",
                    "Percent": 0
                }
            },
            "F": {
                "Choice": "“... passed from one to the next.”",
                "Key": {
                    "Correct": false,
                    "Rationale": "",
                    "Percent": 0
                }
            }
        },
        "Parts": {}
    },
    "19": {
        "Number": 19,
        "Type": "MC",
        "NumChoices": 4,
        "Topics": [
            "Reading Literature - Key Ideas & Details"
        ],
        "SubTopics": [
            "Cite the textual evidence that most strongly supports an analysis of what the text says explicitly as well as inferences drawn from the text."
        ],
        "SuppContent": [
            "problems/MDG8E/supps/MDG8E-S4.json"
        ],
        "SuppTools": [],
        "Points": 1,
        "Explain": false,
        "Content": [
            "Which quotation from the passage from Gathering Blue provides the BEST evidence that Katrina is trusted by the community leaders?"
        ],
        "AnswerChoices": {
            "A": {
                "Choice": "“Once, many years before, Katrina had been asked to replace a few threads that had torn loose.” (paragraph 2)",
                "Key": {
                    "Correct": false,
                    "Rationale": "",
                    "Percent": 0
                }
            },
            "B": {
                "Choice": "“Each year that followed, they had brought the ancient robe again to her mother for small repairs.” (paragraph 4)",
                "Key": {
                    "Correct": true,
                    "Rationale": "",
                    "Percent": 0
                }
            },
            "C": {
                "Choice": "“'One day my daughter will be able to do this,' Katrina had said one year to the guardian.” (paragraph 5)",
                "Key": {
                    "Correct": false,
                    "Rationale": "",
                    "Percent": 0
                }
            },
            "D": {
                "Choice": "“Kira always stood at her mother's side, never touching the fragile ancient cloth...” (paragraph 7)",
                "Key": {
                    "Correct": false,
                    "Rationale": "",
                    "Percent": 0
                }
            }
        },
        "Parts": {}
    },
    "20": {
        "Number": 20,
        "Type": "MP",
        "NumChoices": 0,
        "Topics": [
            "Reading Literature - Key Ideas & Details"
        ],
        "SubTopics": [
            "Analyze how particular lines of dialogue or incidents in a story or drama propel the action, reveal aspects of a character, or provoke a decision."
        ],
        "SuppContent": [
            "problems/MDG8E/supps/MDG8E-S4.json"
        ],
        "SuppTools": [],
        "Points": 2,
        "Explain": false,
        "Content": [
            ":ibox:THIS QUESTION HAS TWO PARTS."
        ],
        "AnswerChoices": {},
        "Parts": {
            "A": {
                "Type": "MC",
                "NumChoices": 4,
                "Points": 1,
                "Explain": false,
                "Content": [
                    "Based on the passage from Gathering Blue, which words BEST describe how Katrina wants the community leaders to think of her daughter, Kira?"
                ],
                "AnswerChoices": {
                    "A": {
                        "Choice": "curious and thoughtful",
                        "Key": {
                            "Correct": false,
                            "Rationale": "",
                            "Percent": 0
                        }
                    },
                    "B": {
                        "Choice": "talented and gifted",
                        "Key": {
                            "Correct": true,
                            "Rationale": "",
                            "Percent": 0
                        }
                    },
                    "C": {
                        "Choice": "considerate and respectful",
                        "Key": {
                            "Correct": false,
                            "Rationale": "",
                            "Percent": 0
                        }
                    },
                    "D": {
                        "Choice": "confident and protective",
                        "Key": {
                            "Correct": false,
                            "Rationale": "",
                            "Percent": 0
                        }
                    }
                }
            },
            "B": {
                "Type": "MC",
                "NumChoices": 4,
                "Points": 1,
                "Explain": false,
                "Content": [
                    "Which quotation from the passage BEST supports the answer to Part A?"
                ],
                "AnswerChoices": {
                    "A": {
                        "Choice": "“Kira was only a small tyke then, but she remembered standing in the cott's shadowed corner when a guardian brought the fabulous robe...” (paragraph 2)",
                        "Key": {
                            "Correct": false,
                            "Rationale": "",
                            "Percent": 0
                        }
                    },
                    "B": {
                        "Choice": "“... both she and her mother had peered from their seats at the stage, trying to find the repaired place as the Singer moved his arms in gestures during the Song.” (paragraph 3)",
                        "Key": {
                            "Correct": false,
                            "Rationale": "",
                            "Percent": 0
                        }
                    },
                    "C": {
                        "Choice": "“'Look what she has done!' she said and showed him the scrap that Kira had just completed, the one that had composed itself so magically in her fingers.” (paragraph 5)",
                        "Key": {
                            "Correct": true,
                            "Rationale": "",
                            "Percent": 0
                        }
                    },
                    "D": {
                        "Choice": "“Kira had stood silently, embarrassed but proud, as the guardian examined the threading she had done.” (paragraph 6)",
                        "Key": {
                            "Correct": false,
                            "Rationale": "",
                            "Percent": 0
                        }
                    }
                }
            }
        }
    },
    "21": {
        "Number": 21,
        "Type": "MC",
        "NumChoices": 4,
        "Topics": [
            "Reading Literature - Craft & Structure"
        ],
        "SubTopics": [
            "Compare and contrast the structure of two or more texts and analyze how the differing structure of each text contributes to its meaning and style."
        ],
        "SuppContent": [
            "problems/MDG8E/supps/MDG8E-S3.json",
            "problems/MDG8E/supps/MDG8E-S4.json"
        ],
        "SuppTools": [],
        "Points": 1,
        "Explain": false,
        "Content": [
            "Which statement BEST describes how the author of each passage uses setting to develop the plot?"
        ],
        "AnswerChoices": {
            "A": {
                "Choice": "The author of the passage from Banner in the Sky uses the setting to emphasize Rudi's desire to connect with others, while the author of the passage from Gathering Blue uses the setting to emphasize Kira and Katrina's desire to isolate from others.",
                "Key": {
                    "Correct": false,
                    "Rationale": "",
                    "Percent": 0
                }
            },
            "B": {
                "Choice": "The author of the passage from Banner in the Sky uses the setting to describe Rudi's effort to improve his skills at climbing, while the author of the passage from Gathering Blue uses the setting to describe how Kira and Katrina take their skills for granted.",
                "Key": {
                    "Correct": false,
                    "Rationale": "",
                    "Percent": 0
                }
            },
            "C": {
                "Choice": "The author of the passage from Banner in the Sky uses the setting to highlight Rudi's connection to the mountains, while the author of the passage from Gathering Blue uses the setting to highlight the connection between Kira and Katrina.",
                "Key": {
                    "Correct": true,
                    "Rationale": "",
                    "Percent": 0
                }
            },
            "D": {
                "Choice": "The author of the passage from Banner in the Sky uses the setting to communicate Rudi's lack of confidence, while the author of the passage from Gathering Blue uses the setting to communicate Kira and Katrina's abundance of confidence.",
                "Key": {
                    "Correct": false,
                    "Rationale": "",
                    "Percent": 0
                }
            }
        },
        "Parts": {}
    },
    "22": {
        "Number": 22,
        "Type": "LR",
        "NumChoices": 0,
        "Topics": [
            "Text Types & Purposes"
        ],
        "SubTopics": [
            "Write informative/explanatory texts to examine a topic and convey ideas, concepts, and information through the selection, organization, and analysis of relevant content."
        ],
        "SuppContent": [
            "problems/MDG8E/supps/MDG8E-S3.json",
            "problems/MDG8E/supps/MDG8E-S4.json"
        ],
        "SuppTools": [],
        "Points": 1,
        "Explain": false,
        "Content": [
            "You have read the passage from Banner in the Sky and the passage from Gathering Blue. Write a response analyzing how the setting of EACH passage impacts the development of the characters. Use evidence from BOTH passages to support your response."
        ],
        "AnswerChoices": {},
        "Parts": {}
    },
    "23": {
        "Number": 23,
        "Type": "MC",
        "NumChoices": 4,
        "Topics": [
            "Reading Information - Craft & Structure"
        ],
        "SubTopics": [
            "Analyze in detail the structure of a specific paragraph in a text, including the role of particular sentences in developing and refining a key concept."
        ],
        "SuppContent": [
            "problems/MDG8E/supps/MDG8E-S5.json"
        ],
        "SuppTools": [],
        "Points": 1,
        "Explain": false,
        "Content": [
            "Which statement BEST explains the structure of paragraph 2 in “Testing Thinking”?"
        ],
        "AnswerChoices": {
            "A": {
                "Choice": "The author contrasts a computer's ability with the human experience.",
                "Key": {
                    "Correct": true,
                    "Rationale": "",
                    "Percent": 0
                }
            },
            "B": {
                "Choice": "The author presents the problem of humans relying on artificial intelligence.",
                "Key": {
                    "Correct": false,
                    "Rationale": "",
                    "Percent": 0
                }
            },
            "C": {
                "Choice": "The author describes the advantages of using computers to answer math problems.",
                "Key": {
                    "Correct": false,
                    "Rationale": "",
                    "Percent": 0
                }
            },
            "D": {
                "Choice": "The author draws parallels between technological growth and human development.",
                "Key": {
                    "Correct": false,
                    "Rationale": "",
                    "Percent": 0
                }
            }
        },
        "Parts": {}
    },
    "24": {
        "Number": 24,
        "Type": "MC",
        "NumChoices": 4,
        "Topics": [
            "Reading Information - Craft & Structure"
        ],
        "SubTopics": [
            "Analyze in detail the structure of a specific paragraph in a text, including the role of particular sentences in developing and refining a key concept."
        ],
        "SuppContent": [
            "problems/MDG8E/supps/MDG8E-S5.json"
        ],
        "SuppTools": [],
        "Points": 1,
        "Explain": false,
        "Content": [
            "What is the main purpose of paragraph 3 in “Testing Thinking”?"
        ],
        "AnswerChoices": {
            "A": {
                "Choice": "to establish a claim that will be defended",
                "Key": {
                    "Correct": false,
                    "Rationale": "",
                    "Percent": 0
                }
            },
            "B": {
                "Choice": "to give additional support to an earlier idea",
                "Key": {
                    "Correct": false,
                    "Rationale": "",
                    "Percent": 0
                }
            },
            "C": {
                "Choice": "to explain the history of a field of study",
                "Key": {
                    "Correct": false,
                    "Rationale": "",
                    "Percent": 0
                }
            },
            "D": {
                "Choice": "to define a concept to be discussed",
                "Key": {
                    "Correct": true,
                    "Rationale": "",
                    "Percent": 0
                }
            }
        },
        "Parts": {}
    },
    "25": {
        "Number": 25,
        "Type": "MC",
        "NumChoices": 4,
        "Topics": [
            "Reading Information - Craft & Structure"
        ],
        "SubTopics": [
            "Analyze in detail the structure of a specific paragraph in a text, including the role of particular sentences in developing and refining a key concept."
        ],
        "SuppContent": [
            "problems/MDG8E/supps/MDG8E-S5.json"
        ],
        "SuppTools": [],
        "Points": 1,
        "Explain": false,
        "Content": [
            "Read this sentence from paragraph 4 of “Testing Thinking.”",
            ":box:When a computer understands our sentences and responds sensibly, we sometimes believe that it's a thinking being.",
            "Which statement BEST explains the significance of this sentence?"
        ],
        "AnswerChoices": {
            "A": {
                "Choice": "It suggests that humans want a computer's response to be more realistic.",
                "Key": {
                    "Correct": false,
                    "Rationale": "",
                    "Percent": 0
                }
            },
            "B": {
                "Choice": "It provides a clear definition of the mental processes that computers use for communication.",
                "Key": {
                    "Correct": false,
                    "Rationale": "",
                    "Percent": 0
                }
            },
            "C": {
                "Choice": "It shows how humans can make inaccurate assumptions about computers based on limited evidence.",
                "Key": {
                    "Correct": true,
                    "Rationale": "",
                    "Percent": 0
                }
            },
            "D": {
                "Choice": "It explains how a computer's mental processes rely on external input in order to communicate.",
                "Key": {
                    "Correct": false,
                    "Rationale": "",
                    "Percent": 0
                }
            }
        },
        "Parts": {}
    },
    "26": {
        "Number": 26,
        "Type": "MC",
        "NumChoices": 4,
        "Topics": [
            "Reading Information - Craft & Structure"
        ],
        "SubTopics": [
            "Determine the meaning of words and phrases as they are used in a text, including figurative, connotative, and technical meanings; analyze the impact of specific word choices on meaning and tone, including analogies or allusions to other texts."
        ],
        "SuppContent": [
            "problems/MDG8E/supps/MDG8E-S6.json"
        ],
        "SuppTools": [],
        "Points": 1,
        "Explain": false,
        "Content": [
            "Which phrase BEST helps the reader understand the effect of the word MASQUERADE as is used in paragraph 1 of the passage from “Am I Human?”"
        ],
        "AnswerChoices": {
            "A": {
                "Choice": "“... envisioned a contest ...”",
                "Key": {
                    "Correct": false,
                    "Rationale": "",
                    "Percent": 0
                }
            },
            "B": {
                "Choice": "“... tries to trick ...”",
                "Key": {
                    "Correct": true,
                    "Rationale": "",
                    "Percent": 0
                }
            },
            "C": {
                "Choice": "“... questions about poetry ...”",
                "Key": {
                    "Correct": false,
                    "Rationale": "",
                    "Percent": 0
                }
            },
            "D": {
                "Choice": "“... making mistakes about arithmetic.”",
                "Key": {
                    "Correct": false,
                    "Rationale": "",
                    "Percent": 0
                }
            }
        },
        "Parts": {}
    },
    "27": {
        "Number": 27,
        "Type": "MS",
        "NumChoices": 5,
        "Topics": [
            "Vocabulary Acquisition & Use"
        ],
        "SubTopics": [
            "Determine or clarify the meaning of unknown and multiple meaning words or phrases based on grade 8 reading and content, choosing flexibly from a range of strategies."
        ],
        "SuppContent": [
            "problems/MDG8E/supps/MDG8E-S6.json"
        ],
        "SuppTools": [],
        "Points": 1,
        "Explain": false,
        "Content": [
            "In paragraph 2 of the excerpt from “Am I Human?,” which TWO phrases BEST help the reader determine the meaning of FEIGNING?"
        ],
        "AnswerChoices": {
            "A": {
                "Choice": "“partly anticipated”",
                "Key": {
                    "Correct": false,
                    "Rationale": "",
                    "Percent": 0
                }
            },
            "B": {
                "Choice": "“must lie to win”",
                "Key": {
                    "Correct": true,
                    "Rationale": "",
                    "Percent": 0
                }
            },
            "C": {
                "Choice": "“that odd twist”",
                "Key": {
                    "Correct": false,
                    "Rationale": "",
                    "Percent": 0
                }
            },
            "D": {
                "Choice": "“not an exception”",
                "Key": {
                    "Correct": false,
                    "Rationale": "",
                    "Percent": 0
                }
            },
            "E": {
                "Choice": "“is to deceive”",
                "Key": {
                    "Correct": true,
                    "Rationale": "",
                    "Percent": 0
                }
            }
        },
        "Parts": {}
    },
    "28": {
        "Number": 28,
        "Type": "MP",
        "NumChoices": 0,
        "Topics": [
            "Reading Information - Key Ideas & Details"
        ],
        "SubTopics": [
            "Cite the textual evidence that most strongly supports an analysis of what the text says explicitly as well as inferences drawn from the text."
        ],
        "SuppContent": [
            "problems/MDG8E/supps/MDG8E-S6.json"
        ],
        "SuppTools": [],
        "Points": 2,
        "Explain": false,
        "Content": [
            ":ibox:THIS QUESTION HAS TWO PARTS."
        ],
        "AnswerChoices": {},
        "Parts": {
            "A": {
                "Type": "MC",
                "NumChoices": 4,
                "Points": 1,
                "Explain": false,
                "Content": [
                    "According to the author of the excerpt “Am I Human?,” what is the main reason the Turing test is not effective?"
                ],
                "AnswerChoices": {
                    "A": {
                        "Choice": "Programmers have learned how to program computers to fool the test.",
                        "Key": {
                            "Correct": true,
                            "Rationale": "",
                            "Percent": 0
                        }
                    },
                    "B": {
                        "Choice": "Computers are now advanced beyond the simple conversations of the test.",
                        "Key": {
                            "Correct": false,
                            "Rationale": "",
                            "Percent": 0
                        }
                    },
                    "C": {
                        "Choice": "Computers can impersonate people in order to confuse the test.",
                        "Key": {
                            "Correct": false,
                            "Rationale": "",
                            "Percent": 0
                        }
                    },
                    "D": {
                        "Choice": "Programmers have created types of conversation not recognized by the test.",
                        "Key": {
                            "Correct": false,
                            "Rationale": "",
                            "Percent": 0
                        }
                    }
                }
            },
            "B": {
                "Type": "MC",
                "NumChoices": 4,
                "Points": 1,
                "Explain": false,
                "Content": [
                    "Which quotation from the excerpt BEST supports the answer to Part A?"
                ],
                "AnswerChoices": {
                    "A": {
                        "Choice": "“Turing envisioned a contest in which a machine tries to trick an interrogator into believing it is human...” (paragraph 1)",
                        "Key": {
                            "Correct": false,
                            "Rationale": "",
                            "Percent": 0
                        }
                    },
                    "B": {
                        "Choice": "“As Turing himself partly anticipated, the trick to winning is mostly not to answer the questions.” (paragraph 2)",
                        "Key": {
                            "Correct": true,
                            "Rationale": "",
                            "Percent": 0
                        }
                    },
                    "C": {
                        "Choice": "“'Eugene Goostman' supposedly 'won' the Turing test by pretending to be a sarcastic 13- year- old boy...” (paragraph 3)",
                        "Key": {
                            "Correct": false,
                            "Rationale": "",
                            "Percent": 0
                        }
                    },
                    "D": {
                        "Choice": "“Clearly, Turing's original test has not withstood the test of time.” (paragraph 4)",
                        "Key": {
                            "Correct": false,
                            "Rationale": "",
                            "Percent": 0
                        }
                    }
                }
            }
        }
    },
    "29": {
        "Number": 29,
        "Type": "MS",
        "NumChoices": 5,
        "Topics": [
            "Reading Information - Key Ideas & Details"
        ],
        "SubTopics": [
            "Analyze how a text makes connections among and distinctions between individuals, ideas, or events (e.g., through comparisons, analogies, or categories)."
        ],
        "SuppContent": [
            "problems/MDG8E/supps/MDG8E-S5.json",
            "problems/MDG8E/supps/MDG8E-S6.json"
        ],
        "SuppTools": [],
        "Points": 1,
        "Explain": false,
        "Content": [
            "The authors of BOTH “Testing Thinking” and the excerpt from “Am I Human?” establish connections between which TWO concepts?"
        ],
        "AnswerChoices": {
            "A": {
                "Choice": "the desire of humans to develop artificial intelligence",
                "Key": {
                    "Correct": false,
                    "Rationale": "",
                    "Percent": 0
                }
            },
            "B": {
                "Choice": "the similarities between human and artificial intelligence",
                "Key": {
                    "Correct": false,
                    "Rationale": "",
                    "Percent": 0
                }
            },
            "C": {
                "Choice": "the development of machines that imitate human behavior",
                "Key": {
                    "Correct": true,
                    "Rationale": "",
                    "Percent": 0
                }
            },
            "D": {
                "Choice": "the practical advances in intelligence tests for computers",
                "Key": {
                    "Correct": false,
                    "Rationale": "",
                    "Percent": 0
                }
            },
            "E": {
                "Choice": "the challenges of measuring the actual intelligence of a computer",
                "Key": {
                    "Correct": true,
                    "Rationale": "",
                    "Percent": 0
                }
            }
        },
        "Parts": {}
    },
    "30": {
        "Number": 30,
        "Type": "LR",
        "NumChoices": 0,
        "Topics": [
            "Text Types & Purposes"
        ],
        "SubTopics": [
            "Write informative/explanatory texts to examine a topic and convey ideas, concepts, and information through the selection, organization, and analysis of relevant content."
        ],
        "SuppContent": [
            "problems/MDG8E/supps/MDG8E-S5.json",
            "problems/MDG8E/supps/MDG8E-S6.json"
        ],
        "SuppTools": [],
        "Points": 1,
        "Explain": false,
        "Content": [
            "After reading both the article “Testing Thinking” and the excerpt from “Am I Human?” write a response to analyze how each author examines the differences in the ways that humans and artificial intelligence process information. Be sure to use evidence from BOTH passages in developing your response."
        ],
        "AnswerChoices": {},
        "Parts": {}
    }
}